[
  {
    "title": "Death Note",
    "images": [
      {
        "name": "L",
        "url": "https://github.com/eueueue292/Death%20Note/L.PNG?raw=true"
      }
    ]
  },
  {
    "title": "Solo Leveling S1",
    "images": [
      {
        "name": "Sung Jinwoo",
        "url": "https://github.com/eueueue292/Solo%20Leveling%20S1/Sung%20Jinwoo.PNG?raw=true"
      }
    ]
  },
  {
    "title": "Invincible",
    "images": [
      {
        "name": "Omni-Man",
        "url": "https://github.com/eueueue292/Invincible/Omni-Man.PNG?raw=true"
      }
    ]
  }
]
